{
    "tenantId": "pb",
    "moduleName": "ws-services-masters",
    "workflowBasedCardPermission": [
      {
        "name": "WS Connection Tax Head Containers",
        "code": "wsConnectionTaxHeadsContainer",
        "active": true,
        "status" : ["PENDING_FOR_FIELD_INSPECTION"],
        "workflow" :["MODIFY","NEW"]
      },
      {
        "name": "WS Connection Tax Head Containers",
        "code": "plumberDetailsContainer",
        "active": true,
        "status" : ["INITIATED","PENDING_FOR_FIELD_INSPECTION","PENDING_FOR_DOCUMENT_VERIFICATION"],
        "workflow" :["MODIFY","NEW"]
      },
      {
        "name": "WS Connection Tax Head Containers",
        "code": "connectiondetailscontainer",
        "active": true,
        "status" : ["INITIATED","PENDING_FOR_FIELD_INSPECTION","PENDING_FOR_DOCUMENT_VERIFICATION"],
        "workflow" :["MODIFY","NEW"]
      },
      {
        "name": "WS Connection Tax Head Containers",
        "code": "activationDetailsContainer",
        "active": true,
        "status" : ["PENDING_FOR_CONNECTION_ACTIVATION"],
        "workflow" :["NEW"]
      },
      {
        "name": "WS Connection Tax Head Containers",
        "code": "activationDetailsContainer",
        "active": true,
        "status" : ["INITIATED","PENDING_FOR_FIELD_INSPECTION","CONNECTION_ACTIVATED"],
        "workflow" :["MODIFY"]
      },
      {
        "name": "Modification Effective from Container",
        "code": "modificationsEffectiveFrom",
        "active": true,
        "status" : ["PENDING_FOR_CONNECTION_ACTIVATION"],
        "workflow" :["MODIFY"]
      },

      {
        "name": "WS Connection Tax Head Containers",
        "code": "plumberDetailsContainer",
        "active": true,
        "status" : ["CONNECTION_ACTIVATED"],
        "workflow" :["MODIFY"]
      },
      {
        "name": "WS Connection Tax Head Containers",
        "code": "connectiondetailscontainer",
        "active": true,
        "status" : ["CONNECTION_ACTIVATED"],
        "workflow" :["MODIFY"]
      } 

      
    ]
  }
  